type2fuzzy/__init__.py
type2fuzzy/display/__init__.py
type2fuzzy/display/generaltype2fuzzysetplot.py
type2fuzzy/display/intervaltype2fuzzysetplot.py
type2fuzzy/display/setplotter.py
type2fuzzy/display/type1fuzzysetplot.py
type2fuzzy/display/zslicetype2fuzzysetplot.py
type2fuzzy/measurement/__init__.py
type2fuzzy/measurement/timemeasurement.py
type2fuzzy/membership/__init__.py
type2fuzzy/membership/alphacuttype1fuzzyset.py
type2fuzzy/membership/crispset.py
type2fuzzy/membership/generaltype2fuzzyset.py
type2fuzzy/membership/generate_gt2mf.py
type2fuzzy/membership/generate_it2fs.py
type2fuzzy/membership/intervaltype2fuzzyset.py
type2fuzzy/membership/secondarymf.py
type2fuzzy/membership/type1fuzzyset.py
type2fuzzy/membership/type1fuzzyvariable.py
type2fuzzy/membership/zslicetype2fuzzyset.py
type2fuzzy/type1_defuzzification/__init__.py
type2fuzzy/type1_defuzzification/cog_defuzzifier.py
type2fuzzy/type1_defuzzification/mom_defuzzifier.py
type2fuzzy/type1_defuzzification/zslice_centroid_defuzzifier.py
type2fuzzy/type_reduction/__init__.py
type2fuzzy/type_reduction/gt2_mendeljohn_reducer.py
type2fuzzy/type_reduction/gt2_partialcentroid_reducer.py
type2fuzzy/type_reduction/it2_karnikmendel_reducer.py
type2fuzzy/type_reduction/zslice_hagras_reducer.py
type2fuzzy-0.1.63.dist-info/LICENSE
type2fuzzy-0.1.63.dist-info/METADATA
type2fuzzy-0.1.63.dist-info/WHEEL
type2fuzzy-0.1.63.dist-info/top_level.txt
type2fuzzy-0.1.63.dist-info/RECORD
