Metadata-Version: 2.1
Name: type2fuzzy
Version: 0.1.63
Summary: Library for type-2 fuzzy logic research
Home-page: https://github.com/carmelgafa/type2fuzzy
Author: Carmel Gafa
Author-email: carmelgafa@gmail.com
License: MIT
Keywords: type-2 fuzzy,type reduction,gt2fs,it2fs
Classifier: Development Status :: 3 - Alpha
Classifier: Intended Audience :: Developers
Classifier: Topic :: Software Development :: Build Tools
Classifier: License :: OSI Approved :: MIT License
Classifier: Programming Language :: Python :: 3
Classifier: Programming Language :: Python :: 3.4
Classifier: Programming Language :: Python :: 3.5
Classifier: Programming Language :: Python :: 3.6
License-File: LICENSE
Requires-Dist: numpy
Requires-Dist: matplotlib
